minimal_bibtex_io/__init__.py
minimal_bibtex_io/tests/resources/example.bib
minimal_bibtex_io_sebastian_achim_mueller-0.0.3.dist-info/LICENSE
minimal_bibtex_io_sebastian_achim_mueller-0.0.3.dist-info/METADATA
minimal_bibtex_io_sebastian_achim_mueller-0.0.3.dist-info/WHEEL
minimal_bibtex_io_sebastian_achim_mueller-0.0.3.dist-info/top_level.txt
minimal_bibtex_io_sebastian_achim_mueller-0.0.3.dist-info/RECORD
