Metadata-Version: 2.1
Name: minimal-bibtex-io-sebastian-achim-mueller
Version: 0.0.3
Summary: A minimal loader and dumper for bibtex-files
Home-page: https://github.com/relleums/minimal_bibtex_io
Author: Sebastian Achim Mueller
Author-email: sebastian-achim.mueller@mpi-hd.mpg.de
License: UNKNOWN
Project-URL: Bug Tracker, https://github.com/relleums/minimal_bibtex_io/issues
Platform: UNKNOWN
Classifier: Programming Language :: Python :: 3
Classifier: License :: OSI Approved :: MIT License
Classifier: Operating System :: OS Independent
Classifier: Intended Audience :: Science/Research
Classifier: Topic :: Text Processing
Classifier: Topic :: Text Processing :: Markup :: LaTeX
Requires-Python: >=3.0
